magicroot/__init__.py
magicroot/attach.py
magicroot/cls.py
magicroot/dic.py
magicroot/errors.py
magicroot/log.py
magicroot/msg.py
magicroot/telegram.py
magicroot/time.py
magicroot/_beta/PCES.py
magicroot/_beta/__init__.py
magicroot/_beta/databranch/__init__.py
magicroot/_beta/databranch/database.py
magicroot/_beta/databranch/database_structures/__analysis_book.py
magicroot/_beta/databranch/database_structures/__default_analysis.py
magicroot/_beta/databranch/database_structures/__init__.py
magicroot/_beta/databranch/database_structures/__sources.py
magicroot/_beta/databranch/database_structures/__table.py
magicroot/_beta/diamondpinky/__init__.py
magicroot/_beta/diamondpinky/balancesheet/__init__.py
magicroot/_beta/diamondpinky/balancesheet/balance.py
magicroot/_beta/diamondpinky/balancesheet/balancesheet.py
magicroot/_beta/diamondpinky/events/__init__.py
magicroot/_beta/diamondpinky/events/events_table.py
magicroot/_beta/fileleaf/__init__.py
magicroot/_beta/fileleaf/csv.py
magicroot/_beta/fileleaf/directories.py
magicroot/_beta/fileleaf/extensions.py
magicroot/_beta/fileleaf/other.py
magicroot/_beta/fileleaf/path.py
magicroot/_beta/fileleaf/zip.py
magicroot/_beta/fileleaf/excel/__init__.py
magicroot/_beta/gardeningtools/__init__.py
magicroot/_beta/gardeningtools/dynamicmethods.py
magicroot/_beta/pysas/__init__.py
magicroot/_beta/pysas/extract_egp.py
magicroot/_beta/pysas/sas_tables.py
magicroot/_beta/smartowl/__init__.py
magicroot/_beta/smartowl/partiallyorderedset.py
magicroot/_beta/smartowl/sorter.py
magicroot/_pub/__init__.py
magicroot/_pub/controler.py
magicroot/_saved/__init__.py
magicroot/_saved/locator.py
magicroot/_tools/__init__.py
magicroot/_tools/_compare/__init__.py
magicroot/_tools/_compare/_compare.py
magicroot/_tools/_compare/_create.py
magicroot/_tools/_compare/_reshape.py
magicroot/_tools/_compare/_select.py
magicroot/_tools/_compare/_types.py
magicroot/beta/PCES.py
magicroot/beta/__init__.py
magicroot/beta/databranch/__init__.py
magicroot-0.1.84.dist-info/LICENSE
magicroot-0.1.84.dist-info/METADATA
magicroot-0.1.84.dist-info/WHEEL
magicroot-0.1.84.dist-info/top_level.txt
magicroot-0.1.84.dist-info/RECORD
