Metadata-Version: 2.1
Name: magicroot
Version: 0.1.84
Summary: Python like magic
Home-page: https://github.com/HephaestusGodOfFire/magicroot
Author: HephaestusGodOfFire
Author-email: author@example.com
License: UNKNOWN
Project-URL: Bug Tracker, https://github.com/HephaestusGodOfFire/magicroot/issues
Platform: UNKNOWN
Classifier: Programming Language :: Python :: 3
Classifier: License :: OSI Approved :: MIT License
Classifier: Operating System :: OS Independent
Requires-Python: >=3.6
License-File: LICENSE
